njinn/__init__.py
njinn/__main__.py
njinn/base.py
njinn/njinn_api.py
njinn/njinn_client.py
njinn/packs.py
njinn/utils.py
njinn/models/__init__.py
njinn/models/config.py
njinn/models/execution.py
njinn/models/group_member.py
njinn/models/mixins.py
njinn/models/njinn_group.py
njinn/models/rule.py
njinn/models/schedule.py
njinn/models/task_execution.py
njinn/models/webhook.py
njinn/models/webhooklog.py
njinn/models/workflow.py
njinn/resources/__init__.py
njinn/resources/config_resource.py
njinn/resources/execution_resource.py
njinn/resources/group_member_resource.py
njinn/resources/mixins.py
njinn/resources/njinn_group_resource.py
njinn/resources/root_resource.py
njinn/resources/rule_resource.py
njinn/resources/schedule_resource.py
njinn/resources/task_execution_resource.py
njinn/resources/webhook_resource.py
njinn/resources/webhooklog_resource.py
njinn/resources/workflow_resource.py
njinn-0.3.2.dist-info/METADATA
njinn-0.3.2.dist-info/WHEEL
njinn-0.3.2.dist-info/entry_points.txt
njinn-0.3.2.dist-info/top_level.txt
njinn-0.3.2.dist-info/RECORD
