Metadata-Version: 2.1
Name: njinn
Version: 0.3.2
Summary: Njinn CLI
Home-page: UNKNOWN
Author: Njinn Technologies GmbH
Author-email: contact@njinn.io
License: Other/Proprietary License
Platform: UNKNOWN
Classifier: License :: Other/Proprietary License
Classifier: Programming Language :: Python :: 3
Classifier: Programming Language :: Python :: 3.7
Classifier: Programming Language :: Python :: Implementation :: CPython
Classifier: Operating System :: OS Independent
Requires-Python: >=3.7
Requires-Dist: click-log (<0.4,>=0.3)
Requires-Dist: click-spinner (<0.2,>=0.1)
Requires-Dist: click (<8.0,>=7.0)
Requires-Dist: gitpython (<2.2,>=2.1)
Requires-Dist: pyyaml (<5.2,>=5.1)
Requires-Dist: requests (<2.22,>=2.21)
